{
    "$schema": "https://marketplace.umbraco.com/umbraco-marketplace-schema.json",
    "AuthorDetails": {
        "Name": "Chalmers Library",
        "Url": "https://github.com/ChalmersLibrary"
    },
    "Category": "Developer Tools",
    "AlternateCategory": "Editor Tools",
    "PackageType": "Package",
    "LicenseTypes": [ "Free" ],
    "DocumentationUrl": "https://github.com/ChalmersLibrary/Umbraco.Community.LinkAudit",
    "IssueTrackerUrl": "https://github.com/ChalmersLibrary/Umbraco.Community.LinkAudit/issues",
    "Tags": [ "link checker", "broken links", "link audit", "seo", "content quality" ]
}
